{
  "bundleIdentifier": "com.electron.realtimeboard",
  "i18n": {
    "defaultLocale": "en",
    "locales": [
      "en",
      "zh-Hans"
    ]
  },
  "categories": [
    {
      "id": "remote.miro.tools",
      "title": {
        "en": "Tools",
        "zh-Hans": "工具"
      },
      "items": [
        {
          "id": "remote.miro.tools.c87bcf867a",
          "title": {
            "en": "Select tool/hand mode",
            "zh-Hans": "选择tool/hand 模式"
          },
          "shortcutConfiguration": {
            "keyCode": 9,
            "carbonModifiers": 0,
            "displayKey": "V"
          }
        },
        {
          "id": "remote.miro.tools.703d441f0a",
          "title": {
            "en": "Text",
            "zh-Hans": "文本"
          },
          "shortcutConfiguration": {
            "keyCode": 17,
            "carbonModifiers": 0,
            "displayKey": "T"
          }
        },
        {
          "id": "remote.miro.tools.e7b3c7174a",
          "title": {
            "en": "Sticky note",
            "zh-Hans": "Sticky 笔记"
          },
          "shortcutConfiguration": {
            "keyCode": 45,
            "carbonModifiers": 0,
            "displayKey": "N"
          }
        },
        {
          "id": "remote.miro.tools.56d1ff4f05",
          "title": {
            "en": "Shapes",
            "zh-Hans": "Shapes"
          },
          "shortcutConfiguration": {
            "keyCode": 1,
            "carbonModifiers": 0,
            "displayKey": "S"
          }
        },
        {
          "id": "remote.miro.tools.aa54a8dbef",
          "title": {
            "en": "Rectangle",
            "zh-Hans": "Rectangle"
          },
          "shortcutConfiguration": {
            "keyCode": 15,
            "carbonModifiers": 0,
            "displayKey": "R"
          }
        },
        {
          "id": "remote.miro.tools.d9502720d5",
          "title": {
            "en": "Oval",
            "zh-Hans": "Oval"
          },
          "shortcutConfiguration": {
            "keyCode": 31,
            "carbonModifiers": 0,
            "displayKey": "O"
          }
        },
        {
          "id": "remote.miro.tools.0409e1b684",
          "title": {
            "en": "Connection Line, arrow",
            "zh-Hans": "Connection 行, arrow"
          },
          "shortcutConfiguration": {
            "keyCode": 37,
            "carbonModifiers": 0,
            "displayKey": "L"
          }
        },
        {
          "id": "remote.miro.tools.1e7ed1d3bd",
          "title": {
            "en": "Card",
            "zh-Hans": "Card"
          },
          "shortcutConfiguration": {
            "keyCode": 2,
            "carbonModifiers": 0,
            "displayKey": "D"
          }
        },
        {
          "id": "remote.miro.tools.e2a9a70183",
          "title": {
            "en": "Pen",
            "zh-Hans": "Pen"
          },
          "shortcutConfiguration": {
            "keyCode": 35,
            "carbonModifiers": 0,
            "displayKey": "P"
          }
        },
        {
          "id": "remote.miro.tools.e840e3f6e3",
          "title": {
            "en": "Eraser",
            "zh-Hans": "Eraser"
          },
          "shortcutConfiguration": {
            "keyCode": 14,
            "carbonModifiers": 0,
            "displayKey": "E"
          }
        },
        {
          "id": "remote.miro.tools.0b82414aee",
          "title": {
            "en": "Comment",
            "zh-Hans": "评论"
          },
          "shortcutConfiguration": {
            "keyCode": 8,
            "carbonModifiers": 0,
            "displayKey": "C"
          }
        },
        {
          "id": "remote.miro.tools.ed7a88faad",
          "title": {
            "en": "Undo",
            "zh-Hans": "撤消"
          },
          "shortcutConfiguration": {
            "keyCode": 6,
            "carbonModifiers": 256,
            "displayKey": "Z"
          }
        },
        {
          "id": "remote.miro.tools.01e40b71a0",
          "title": {
            "en": "Redo",
            "zh-Hans": "恢复"
          },
          "shortcutConfiguration": {
            "keyCode": 6,
            "carbonModifiers": 768,
            "displayKey": "Z"
          }
        },
        {
          "id": "remote.miro.tools.6eedd02e69",
          "title": {
            "en": "Frames",
            "zh-Hans": "Frames"
          },
          "shortcutConfiguration": {
            "keyCode": 3,
            "carbonModifiers": 0,
            "displayKey": "F"
          }
        },
        {
          "id": "remote.miro.tools.d9b9e279de",
          "title": {
            "en": "Minimap",
            "zh-Hans": "迷你地图"
          },
          "shortcutConfiguration": {
            "keyCode": 46,
            "carbonModifiers": 0,
            "displayKey": "M"
          }
        },
        {
          "id": "remote.miro.tools.fcba3e3323",
          "title": {
            "en": "Link to",
            "zh-Hans": "Link to"
          },
          "shortcutConfiguration": {
            "keyCode": 40,
            "carbonModifiers": 256,
            "displayKey": "K"
          }
        },
        {
          "id": "remote.miro.tools.caca001522",
          "title": {
            "en": "New sticky note in bulk mode",
            "zh-Hans": "New sticky note in bulk mode"
          },
          "shortcutConfiguration": {
            "keyCode": 36,
            "carbonModifiers": 0,
            "displayKey": "36"
          }
        },
        {
          "id": "remote.miro.tools.4393e229f4",
          "title": {
            "en": "Exit sticky note bulk mode",
            "zh-Hans": "Exit sticky note bulk mode"
          },
          "shortcutConfiguration": {
            "keyCode": 53,
            "carbonModifiers": 0,
            "displayKey": "⎋"
          }
        }
      ]
    },
    {
      "id": "remote.miro.general",
      "title": {
        "en": "General",
        "zh-Hans": "通用"
      },
      "items": [
        {
          "id": "remote.miro.general.353a1a9612",
          "title": {
            "en": "Copy",
            "zh-Hans": "复制"
          },
          "shortcutConfiguration": {
            "keyCode": 8,
            "carbonModifiers": 256,
            "displayKey": "C"
          }
        },
        {
          "id": "remote.miro.general.884509fe94",
          "title": {
            "en": "Paste",
            "zh-Hans": "粘贴"
          },
          "shortcutConfiguration": {
            "keyCode": 9,
            "carbonModifiers": 256,
            "displayKey": "V"
          }
        },
        {
          "id": "remote.miro.general.c3bbda670e",
          "title": {
            "en": "Cut",
            "zh-Hans": "剪切"
          },
          "shortcutConfiguration": {
            "keyCode": 7,
            "carbonModifiers": 256,
            "displayKey": "X"
          }
        },
        {
          "id": "remote.miro.general.cbbe72094e",
          "title": {
            "en": "Duplicate",
            "zh-Hans": "创建副本"
          },
          "shortcutConfiguration": {
            "keyCode": 2,
            "carbonModifiers": 256,
            "displayKey": "D"
          }
        },
        {
          "id": "remote.miro.general.5119959848",
          "title": {
            "en": "Duplicate horizontally or vertically",
            "zh-Hans": "Duplicate horizontally or vertically"
          },
          "shortcutConfiguration": {
            "keyCode": 123,
            "carbonModifiers": 2048,
            "displayKey": "←"
          }
        },
        {
          "id": "remote.miro.general.b6afaa013a",
          "title": {
            "en": "Duplicate horizontally or vertically",
            "zh-Hans": "Duplicate horizontally or vertically"
          },
          "shortcutConfiguration": {
            "keyCode": 124,
            "carbonModifiers": 2048,
            "displayKey": "→"
          }
        },
        {
          "id": "remote.miro.general.fe3be3e684",
          "title": {
            "en": "Duplicate horizontally or vertically",
            "zh-Hans": "Duplicate horizontally or vertically"
          },
          "shortcutConfiguration": {
            "keyCode": 126,
            "carbonModifiers": 2048,
            "displayKey": "↑"
          }
        },
        {
          "id": "remote.miro.general.a4d29def9f",
          "title": {
            "en": "Duplicate horizontally or vertically",
            "zh-Hans": "Duplicate horizontally or vertically"
          },
          "shortcutConfiguration": {
            "keyCode": 125,
            "carbonModifiers": 2048,
            "displayKey": "↓"
          }
        },
        {
          "id": "remote.miro.general.ae99da7148",
          "title": {
            "en": "Select all",
            "zh-Hans": "全选"
          },
          "shortcutConfiguration": {
            "keyCode": 0,
            "carbonModifiers": 256,
            "displayKey": "A"
          }
        },
        {
          "id": "remote.miro.general.05adc25195",
          "title": {
            "en": "Edit selected item",
            "zh-Hans": "编辑 所选 项目"
          },
          "shortcutConfiguration": {
            "keyCode": 36,
            "carbonModifiers": 0,
            "displayKey": "36"
          }
        },
        {
          "id": "remote.miro.general.7166018e84",
          "title": {
            "en": "Deselect, quit edit, switch to cursor",
            "zh-Hans": "Deselect, quit edit, switch to cursor"
          },
          "shortcutConfiguration": {
            "keyCode": 53,
            "carbonModifiers": 0,
            "displayKey": "⎋"
          }
        },
        {
          "id": "remote.miro.general.d20b297676",
          "title": {
            "en": "Delete",
            "zh-Hans": "删除"
          },
          "shortcutConfiguration": {
            "keyCode": 51,
            "carbonModifiers": 0,
            "displayKey": "⌫"
          }
        },
        {
          "id": "remote.miro.general.b0fb87819e",
          "title": {
            "en": "Group",
            "zh-Hans": "编组"
          },
          "shortcutConfiguration": {
            "keyCode": 5,
            "carbonModifiers": 256,
            "displayKey": "G"
          }
        },
        {
          "id": "remote.miro.general.fcfb48217e",
          "title": {
            "en": "Ungroup",
            "zh-Hans": "取消编组"
          },
          "shortcutConfiguration": {
            "keyCode": 5,
            "carbonModifiers": 768,
            "displayKey": "G"
          }
        },
        {
          "id": "remote.miro.general.c95c7a16e0",
          "title": {
            "en": "Lock / Unlock",
            "zh-Hans": "Lock / Unlock"
          },
          "shortcutConfiguration": {
            "keyCode": 37,
            "carbonModifiers": 256,
            "displayKey": "L"
          }
        },
        {
          "id": "remote.miro.general.c8689b59b2",
          "title": {
            "en": "Protected lock/unprotected lock",
            "zh-Hans": "Protected lock/unprotected lock"
          },
          "shortcutConfiguration": {
            "keyCode": 37,
            "carbonModifiers": 768,
            "displayKey": "L"
          }
        },
        {
          "id": "remote.miro.general.9e3dc164a2",
          "title": {
            "en": "Send to front",
            "zh-Hans": "Send to front"
          },
          "shortcutConfiguration": {
            "keyCode": 126,
            "carbonModifiers": 0,
            "displayKey": "↑"
          }
        },
        {
          "id": "remote.miro.general.a2d65b6f9f",
          "title": {
            "en": "Send to back",
            "zh-Hans": "Send to back"
          },
          "shortcutConfiguration": {
            "keyCode": 125,
            "carbonModifiers": 0,
            "displayKey": "↓"
          }
        }
      ]
    },
    {
      "id": "remote.miro.navigation",
      "title": {
        "en": "Navigation",
        "zh-Hans": "导航"
      },
      "items": [
        {
          "id": "remote.miro.navigation.2c64a20c3f",
          "title": {
            "en": "Move items / canvas",
            "zh-Hans": "移动items / 画布"
          },
          "shortcutConfiguration": {
            "keyCode": 123,
            "carbonModifiers": 0,
            "displayKey": "←"
          }
        },
        {
          "id": "remote.miro.navigation.fb75a74e74",
          "title": {
            "en": "Move items / canvas",
            "zh-Hans": "移动items / 画布"
          },
          "shortcutConfiguration": {
            "keyCode": 124,
            "carbonModifiers": 0,
            "displayKey": "→"
          }
        },
        {
          "id": "remote.miro.navigation.1bbea4c5df",
          "title": {
            "en": "Move items / canvas",
            "zh-Hans": "移动items / 画布"
          },
          "shortcutConfiguration": {
            "keyCode": 126,
            "carbonModifiers": 0,
            "displayKey": "↑"
          }
        },
        {
          "id": "remote.miro.navigation.b75475537f",
          "title": {
            "en": "Move items / canvas",
            "zh-Hans": "移动items / 画布"
          },
          "shortcutConfiguration": {
            "keyCode": 125,
            "carbonModifiers": 0,
            "displayKey": "↓"
          }
        },
        {
          "id": "remote.miro.navigation.e4a221a9a6",
          "title": {
            "en": "Zoom in",
            "zh-Hans": "放大"
          },
          "shortcutConfiguration": {
            "keyCode": 24,
            "carbonModifiers": 256,
            "displayKey": "="
          }
        },
        {
          "id": "remote.miro.navigation.9b361287d7",
          "title": {
            "en": "Zoom out",
            "zh-Hans": "缩小"
          },
          "shortcutConfiguration": {
            "keyCode": 27,
            "carbonModifiers": 256,
            "displayKey": "-"
          }
        },
        {
          "id": "remote.miro.navigation.43fe116d8b",
          "title": {
            "en": "Zoom to 100%",
            "zh-Hans": "缩放到 100%"
          },
          "shortcutConfiguration": {
            "keyCode": 29,
            "carbonModifiers": 256,
            "displayKey": "0"
          }
        },
        {
          "id": "remote.miro.navigation.3f940be675",
          "title": {
            "en": "Zoom to fit",
            "zh-Hans": "Zoom to fit"
          },
          "shortcutConfiguration": {
            "keyCode": 18,
            "carbonModifiers": 2048,
            "displayKey": "1"
          }
        },
        {
          "id": "remote.miro.navigation.945356dabc",
          "title": {
            "en": "Zoom to selected item",
            "zh-Hans": "Zoom to selected item"
          },
          "shortcutConfiguration": {
            "keyCode": 19,
            "carbonModifiers": 2048,
            "displayKey": "2"
          }
        },
        {
          "id": "remote.miro.navigation.18e419a5b4",
          "title": {
            "en": "Toggle grid",
            "zh-Hans": "切换网格"
          },
          "shortcutConfiguration": {
            "keyCode": 5,
            "carbonModifiers": 0,
            "displayKey": "G"
          }
        },
        {
          "id": "remote.miro.navigation.f064aa4339",
          "title": {
            "en": "Search",
            "zh-Hans": "搜索"
          },
          "shortcutConfiguration": {
            "keyCode": 3,
            "carbonModifiers": 256,
            "displayKey": "F"
          }
        }
      ]
    },
    {
      "id": "remote.miro.text",
      "title": {
        "en": "Text",
        "zh-Hans": "文本"
      },
      "items": [
        {
          "id": "remote.miro.text.06e14ba6de",
          "title": {
            "en": "Bold",
            "zh-Hans": "加粗"
          },
          "shortcutConfiguration": {
            "keyCode": 11,
            "carbonModifiers": 256,
            "displayKey": "B"
          }
        },
        {
          "id": "remote.miro.text.5760178660",
          "title": {
            "en": "Italic",
            "zh-Hans": "斜体"
          },
          "shortcutConfiguration": {
            "keyCode": 34,
            "carbonModifiers": 256,
            "displayKey": "I"
          }
        },
        {
          "id": "remote.miro.text.e9b85c2f0a",
          "title": {
            "en": "Underline",
            "zh-Hans": "下划线"
          },
          "shortcutConfiguration": {
            "keyCode": 32,
            "carbonModifiers": 256,
            "displayKey": "U"
          }
        }
      ]
    }
  ]
}
